{
  "leaderboard": [
    {
      "name": "meliziana",
      "balance": 1411,
      "totalEarned": 3806,
      "totalSpent": 2395,
      "gamesPlayed": 73,
      "gamesWon": 31,
      "streak": 3
    },
    {
      "name": "guest567432",
      "balance": 1196,
      "totalEarned": 1196,
      "totalSpent": 0,
      "gamesPlayed": 0,
      "gamesWon": 0,
      "streak": 3
    },
    {
      "name": "muzlamic",
      "balance": 1175,
      "totalEarned": 2025,
      "totalSpent": 850,
      "gamesPlayed": 82,
      "gamesWon": 31,
      "streak": 3
    },
    {
      "name": "tevb0t",
      "balance": 1116,
      "totalEarned": 1126,
      "totalSpent": 10,
      "gamesPlayed": 1,
      "gamesWon": 0,
      "streak": 3
    },
    {
      "name": "shance",
      "balance": 939,
      "totalEarned": 884,
      "totalSpent": 192,
      "gamesPlayed": 14,
      "gamesWon": 6,
      "streak": 3
    },
    {
      "name": "peakyc0",
      "balance": 920,
      "totalEarned": 940,
      "totalSpent": 20,
      "gamesPlayed": 2,
      "gamesWon": 2,
      "streak": 3
    },
    {
      "name": "poseidon_o7",
      "balance": 878,
      "totalEarned": 878,
      "totalSpent": 0,
      "gamesPlayed": 0,
      "gamesWon": 0,
      "streak": 3
    },
    {
      "name": "faddy4u",
      "balance": 798,
      "totalEarned": 1723,
      "totalSpent": 925,
      "gamesPlayed": 77,
      "gamesWon": 28,
      "streak": 3
    },
    {
      "name": "nitro_st",
      "balance": 726,
      "totalEarned": 726,
      "totalSpent": 0,
      "gamesPlayed": 0,
      "gamesWon": 0,
      "streak": 3
    },
    {
      "name": "hittittt",
      "balance": 710,
      "totalEarned": 710,
      "totalSpent": 0,
      "gamesPlayed": 0,
      "gamesWon": 0,
      "streak": 3
    },
    {
      "name": "neinswein",
      "balance": 676,
      "totalEarned": 676,
      "totalSpent": 0,
      "gamesPlayed": 0,
      "gamesWon": 0,
      "streak": 3
    },
    {
      "name": "damiybe",
      "balance": 652,
      "totalEarned": 662,
      "totalSpent": 10,
      "gamesPlayed": 1,
      "gamesWon": 0,
      "streak": 3
    },
    {
      "name": "plebcentral",
      "balance": 625,
      "totalEarned": 625,
      "totalSpent": 0,
      "gamesPlayed": 0,
      "gamesWon": 0,
      "streak": 2
    },
    {
      "name": "bounty44",
      "balance": 623,
      "totalEarned": 623,
      "totalSpent": 0,
      "gamesPlayed": 0,
      "gamesWon": 0,
      "streak": 2
    },
    {
      "name": "skibidi_toiiet",
      "balance": 621,
      "totalEarned": 846,
      "totalSpent": 225,
      "gamesPlayed": 5,
      "gamesWon": 2,
      "streak": 3
    },
    {
      "name": "papaah",
      "balance": 616,
      "totalEarned": 616,
      "totalSpent": 0,
      "gamesPlayed": 0,
      "gamesWon": 0,
      "streak": 3
    },
    {
      "name": "neincs",
      "balance": 613,
      "totalEarned": 613,
      "totalSpent": 0,
      "gamesPlayed": 0,
      "gamesWon": 0,
      "streak": 2
    },
    {
      "name": "politecatt",
      "balance": 600,
      "totalEarned": 650,
      "totalSpent": 50,
      "gamesPlayed": 3,
      "gamesWon": 1,
      "streak": 3
    },
    {
      "name": "iraqibaldmidget",
      "balance": 595,
      "totalEarned": 595,
      "totalSpent": 0,
      "gamesPlayed": 0,
      "gamesWon": 0,
      "streak": 1
    },
    {
      "name": "alexmesq",
      "balance": 584,
      "totalEarned": 584,
      "totalSpent": 0,
      "gamesPlayed": 0,
      "gamesWon": 0,
      "streak": 3
    },
    {
      "name": "s1nc3",
      "balance": 570,
      "totalEarned": 625,
      "totalSpent": 55,
      "gamesPlayed": 7,
      "gamesWon": 1,
      "streak": 3
    },
    {
      "name": "nas_3",
      "balance": 566,
      "totalEarned": 566,
      "totalSpent": 0,
      "gamesPlayed": 0,
      "gamesWon": 0,
      "streak": 3
    },
    {
      "name": "kingirnfist",
      "balance": 561,
      "totalEarned": 561,
      "totalSpent": 0,
      "gamesPlayed": 0,
      "gamesWon": 0,
      "streak": 2
    },
    {
      "name": "matthiasdemir",
      "balance": 560,
      "totalEarned": 959,
      "totalSpent": 399,
      "gamesPlayed": 5,
      "gamesWon": 2,
      "streak": 3
    },
    {
      "name": "quantik",
      "balance": 549,
      "totalEarned": 549,
      "totalSpent": 0,
      "gamesPlayed": 0,
      "gamesWon": 0,
      "streak": 2
    },
    {
      "name": "5pray",
      "balance": 546,
      "totalEarned": 546,
      "totalSpent": 0,
      "gamesPlayed": 0,
      "gamesWon": 0,
      "streak": 3
    },
    {
      "name": "lostinplacex",
      "balance": 544,
      "totalEarned": 544,
      "totalSpent": 0,
      "gamesPlayed": 0,
      "gamesWon": 0,
      "streak": 3
    },
    {
      "name": "lena_xc",
      "balance": 538,
      "totalEarned": 538,
      "totalSpent": 0,
      "gamesPlayed": 0,
      "gamesWon": 0,
      "streak": 3
    },
    {
      "name": "patwifi",
      "balance": 526,
      "totalEarned": 526,
      "totalSpent": 0,
      "gamesPlayed": 0,
      "gamesWon": 0,
      "streak": 3
    },
    {
      "name": "xingxingmonkey",
      "balance": 521,
      "totalEarned": 546,
      "totalSpent": 25,
      "gamesPlayed": 1,
      "gamesWon": 1,
      "streak": 3
    },
    {
      "name": "yshy_02222",
      "balance": 521,
      "totalEarned": 521,
      "totalSpent": 0,
      "gamesPlayed": 0,
      "gamesWon": 0,
      "streak": 2
    },
    {
      "name": "xx_i_garrem_deez_xx",
      "balance": 520,
      "totalEarned": 520,
      "totalSpent": 0,
      "gamesPlayed": 0,
      "gamesWon": 0,
      "streak": 3
    },
    {
      "name": "lluboc",
      "balance": 515,
      "totalEarned": 515,
      "totalSpent": 0,
      "gamesPlayed": 0,
      "gamesWon": 0,
      "streak": 2
    },
    {
      "name": "tacticoolbrucey",
      "balance": 514,
      "totalEarned": 723,
      "totalSpent": 209,
      "gamesPlayed": 4,
      "gamesWon": 3,
      "streak": 2
    },
    {
      "name": "comradeahmed1",
      "balance": 507,
      "totalEarned": 507,
      "totalSpent": 0,
      "gamesPlayed": 0,
      "gamesWon": 0,
      "streak": 2
    },
    {
      "name": "omazed",
      "balance": 501,
      "totalEarned": 501,
      "totalSpent": 0,
      "gamesPlayed": 0,
      "gamesWon": 0,
      "streak": 2
    },
    {
      "name": "gr4ntie",
      "balance": 476,
      "totalEarned": 476,
      "totalSpent": 0,
      "gamesPlayed": 0,
      "gamesWon": 0,
      "streak": 3
    },
    {
      "name": "karmahit",
      "balance": 474,
      "totalEarned": 474,
      "totalSpent": 0,
      "gamesPlayed": 0,
      "gamesWon": 0,
      "streak": 3
    },
    {
      "name": "new_jigger",
      "balance": 471,
      "totalEarned": 1251,
      "totalSpent": 780,
      "gamesPlayed": 35,
      "gamesWon": 11,
      "streak": 2
    },
    {
      "name": "bulltalk",
      "balance": 469,
      "totalEarned": 469,
      "totalSpent": 0,
      "gamesPlayed": 0,
      "gamesWon": 0,
      "streak": 2
    },
    {
      "name": "margret02",
      "balance": 458,
      "totalEarned": 458,
      "totalSpent": 0,
      "gamesPlayed": 0,
      "gamesWon": 0,
      "streak": 3
    },
    {
      "name": "crazyhorsel",
      "balance": 456,
      "totalEarned": 531,
      "totalSpent": 75,
      "gamesPlayed": 8,
      "gamesWon": 4,
      "streak": 3
    },
    {
      "name": "skullyontop",
      "balance": 454,
      "totalEarned": 464,
      "totalSpent": 10,
      "gamesPlayed": 1,
      "gamesWon": 1,
      "streak": 3
    },
    {
      "name": "schitt",
      "balance": 442,
      "totalEarned": 442,
      "totalSpent": 0,
      "gamesPlayed": 0,
      "gamesWon": 0,
      "streak": 3
    },
    {
      "name": "johnny2fatty",
      "balance": 440,
      "totalEarned": 600,
      "totalSpent": 160,
      "gamesPlayed": 16,
      "gamesWon": 7,
      "streak": 3
    },
    {
      "name": "xfaisalz1",
      "balance": 436,
      "totalEarned": 4623,
      "totalSpent": 4187,
      "gamesPlayed": 75,
      "gamesWon": 24,
      "streak": 3
    },
    {
      "name": "m0535fps",
      "balance": 435,
      "totalEarned": 560,
      "totalSpent": 125,
      "gamesPlayed": 4,
      "gamesWon": 1,
      "streak": 2
    },
    {
      "name": "sonofarnis",
      "balance": 434,
      "totalEarned": 434,
      "totalSpent": 0,
      "gamesPlayed": 0,
      "gamesWon": 0,
      "streak": 3
    },
    {
      "name": "darth70",
      "balance": 433,
      "totalEarned": 433,
      "totalSpent": 0,
      "gamesPlayed": 0,
      "gamesWon": 0,
      "streak": 2
    },
    {
      "name": "seraj21",
      "balance": 429,
      "totalEarned": 158814,
      "totalSpent": 158385,
      "gamesPlayed": 1350,
      "gamesWon": 490,
      "streak": 3
    }
  ],
  "stats": {
    "totalPlayers": 448,
    "totalCirculating": 121121,
    "totalGames": 2253,
    "pointsPerMessage": 2,
    "dailyBonus": 50
  },
  "costs": {
    "slots": 10,
    "coinflip": 5,
    "dice": 5,
    "rps": 5,
    "blackjack": 25,
    "fight": 10,
    "8ball": 0,
    "duel_min": 10,
    "duel_max": 10000,
    "sr": 50
  },
  "payouts": {
    "slots_jackpot": 1500,
    "slots_quad": 250,
    "slots_triple": 65,
    "slots_twopair": 30,
    "slots_pair": 3,
    "coinflip_win": 10,
    "dice_high": 15,
    "dice_doubles": 20,
    "rps_win": 10,
    "bj_win": 50,
    "bj_blackjack": 75,
    "bj_push": 25,
    "bj_double_win": 100,
    "fight_win": 20
  },
  "lastUpdated": "2026-03-01T17:11:08.382Z"
}